buvar_aiohttp/__init__.py
buvar_aiohttp/attrs.py
buvar_aiohttp/json.py
buvar_aiohttp/testing.py
buvar_aiohttp-0.4.5.dist-info/LICENSE-APACHE
buvar_aiohttp-0.4.5.dist-info/LICENSE-MIT
buvar_aiohttp-0.4.5.dist-info/METADATA
buvar_aiohttp-0.4.5.dist-info/WHEEL
buvar_aiohttp-0.4.5.dist-info/entry_points.txt
buvar_aiohttp-0.4.5.dist-info/top_level.txt
buvar_aiohttp-0.4.5.dist-info/RECORD
